emmett_crypto-0.6.0.dist-info/METADATA
emmett_crypto-0.6.0.dist-info/WHEEL
emmett_crypto-0.6.0.dist-info/license_files/LICENSE
emmett_crypto.libs/libgcc_s-60abea67.so.1
emmett_crypto/py.typed
emmett_crypto/kdf.py
emmett_crypto/symmetric.py
emmett_crypto/__init__.py
emmett_crypto/_crypto.pyi
emmett_crypto/utils.py
emmett_crypto/ciphers.py
emmett_crypto/_crypto.cpython-39-aarch64-linux-gnu.so
emmett_crypto-0.6.0.dist-info/RECORD
